phonobyte/__init__.py
phonobyte/encoder.py
tests/__init__.py
tests/test_encoder.py
phonobyte-0.2.dist-info/LICENSE
phonobyte-0.2.dist-info/METADATA
phonobyte-0.2.dist-info/WHEEL
phonobyte-0.2.dist-info/top_level.txt
phonobyte-0.2.dist-info/RECORD
