Metadata-Version: 2.1
Name: phonobyte
Version: 0.2
Summary: Encoding bytes to phonetically pronounceable words. 
Home-page: https://github.com/meeb/phonobyte
Author: meeb@meeb.org
Author-email: meeb@meeb.org
License: LGPLv3
Download-URL: https://github.com/meeb/phonobyte/tarball/0.1
Keywords: phonobyte
Platform: UNKNOWN
Classifier: Development Status :: 5 - Production/Stable
Classifier: Intended Audience :: Developers
Classifier: License :: OSI Approved :: GNU Lesser General Public License v3 or later (LGPLv3+)
Classifier: Operating System :: OS Independent
Classifier: Programming Language :: Python
Classifier: Programming Language :: Python :: 2
Classifier: Programming Language :: Python :: 2.7
Classifier: Programming Language :: Python :: 3
Classifier: Programming Language :: Python :: 3.3
Classifier: Programming Language :: Python :: 3.4
Classifier: Programming Language :: Python :: 3.5
Classifier: Programming Language :: Python :: 3.6
Classifier: Topic :: Software Development :: Libraries :: Python Modules
